README.md
setup.py
osysid/__init__.py
osysid/_online_linear_model.py
osysid/_online_model.py
osysid.egg-info/PKG-INFO
osysid.egg-info/SOURCES.txt
osysid.egg-info/dependency_links.txt
osysid.egg-info/requires.txt
osysid.egg-info/top_level.txt