Metadata-Version: 2.1
Name: osysid
Version: 0.1.9
Summary: Efficient data-driven online model learning (system identification) and control
Home-page: https://github.com/haozhg/osysid
Author: Hao Zhang
Author-email: haozhang@alumni.princeton.edu
License: MIT
Platform: UNKNOWN
Classifier: License :: OSI Approved :: MIT License
Classifier: Programming Language :: Python :: 3
Classifier: Programming Language :: Python :: 3.7
